LICENSE
MANIFEST.in
README.rst
setup.py
addle/__init__.py
addle/admin.py
addle/apps.py
addle/models.py
addle/tests.py
addle/views.py
addle/migrations/__init__.py
addle_standalone/__init__.py
addle_standalone/settings.py
addle_standalone/urls.py
addle_standalone/wsgi.py
django_addle.egg-info/PKG-INFO
django_addle.egg-info/SOURCES.txt
django_addle.egg-info/dependency_links.txt
django_addle.egg-info/top_level.txt